{
  "Christ": [
    "Wood of the True Cross",
    "Small Rock Fragment from Holy Sepulchre",
    "Linen Fibers from the Shroud of Turin",
    "Sudarium of Oviedo (face-cloth of Christ)"
  ],
  "Mary": [
    "Pieces of her Veil",
    "Stone Fragment from her Holy Sepulchre, Mt. of Olives"
  ],
  "A-C": [
    "Agnes of Rome",
    "Agrippina of Rome",
    "Alexander of Alexandria",
    "Alexius of Edessa & Rome",
    "Ambrose of Milan",
    "Ananias of Damascus",
    "Anastasia of Rome",
    "Anastasia of Sirmium",
    "Andrew the Apostle",
    "Anne (Mother of the Virgin Mary)",
    "Anonymous Martyr (Expeditus)",
    "Anthony the Great of Egypt",
    "Anthony of Padua",
    "Apollonia of Alexandria",
    "Aquila of Corinth",
    "Athanasius of Alexandria",
    "Augustine of Hippo",
    "Bacchus the Martyr",
    "Balthasar (Magi)",
    "Barbara of Nicomedia",
    "Barnabas (Disciple of St. Paul)",
    "Barsanuphius the Great of Gaza",
    "Bartholomew the Apostle",
    "Basil the Elder",
    "Basil the Great",
    "Basil (Vasiľ) Hopko of Prešov & Martyr",
    "Benedict Joseph Labre",
    "Benedict of Nursia",
    "Bernadette Soubirous of Lourdes",
    "Bibiana (Viviana) of Rome",
    "Blaise of Sebaste",
    "Boniface of Tarsus",
    "Boris of Kiev",
    "Callistus I of Rome",
    "Caspar (Magi)",
    "Catherine of Alexandria",
    "Cecilia of Rome",
    "Charbel Makhlouf",
    "Crescentius of Rome",
    "Christina of Persia",
    "Chrysogonus of Aquileia",
    "Clare of Assisi",
    "Clement of Alexandria",
    "Clement I of Rome",
    "Clement the Martyr",
    "Constantine the Great",
    "Cornelius the Centurion",
    "Cornelius of Rome",
    "Corona of Damascus",
    "Cosmas the Physician",
    "Cunegunda of Luxembourg",
    "Cyprian of Carthage",
    "Cyriacus of Attala, Pamphylia (Boy Martyr)",
    "Cyril (Apostle to the Slavs)",
    "Cyril of Alexandria",
    "Cyril of Jerusalem"
  ],
  "D-G": [
    "Damian the Physician",
    "Demetrius of Thessaloniki",
    "Deodatus of Antioch",
    "Dionysius the Areopagite",
    "Dismas the Penitent Thief",
    "Diodatus of Antioch",
    "Donatus the Confessor of Euroea",
    "Dymphna the Virgin Martyr",
    "Elizabeth the Righteous",
    "Emilia of Cappadocia",
    "Ephraem the Syrian",
    "Eugenius of Trebizond",
    "Eulalia of Barcelona",
    "Expeditus of Rome",
    "Faustina Kowalska of the Blessed Sacrament",
    "Felicia the Martyr of Carthage",
    "Felicitas of Rome",
    "Francis of Assisi",
    "Fructuosus of Tarragona",
    "Gemma of Lucca",
    "George of Lydda",
    "Gleb th Passion Bearer",
    "Gregory the Theologian",
    "Gregory of Nyssa"
  ],
  "H-L": [
    "Helena of Constantine",
    "Hilarion the Great",
    "Henry I (Holy Roman Emperor)",
    "Hippolytus of Rome",
    "Holy Innocents",
    "Hubert Liège",
    "Ignatius of Antioch",
    "Irene of Thessaloniki",
    "Jacinta Marto",
    "James the Greater",
    "James the Just",
    "James the Lesser",
    "Januarius I of Benevento",
    "Jerome of Stridon",
    "Joachim the Father of the Virgin Mary",
    "John the Apostle",
    "John the Baptist",
    "John de Brebeuf",
    "John Chrysostom",
    "John of Damascus",
    "John Fisher",
    "John Neumann",
    "John Paul II",
    "John the Varangian of Kiev",
    "Joseph of Nazareth",
    "Joseph of Arimathea",
    "Jucunda of Nicomedia",
    "Jude Thaddeus the Apostle",
    "Juliana of Nicomedia",
    "Julius I of Rome",
    "Justin Martyr",
    "Justina of Antioch",
    "Kateri Tekakwitha",
    "Lawrence of Rome",
    "Lazarus of Bethany",
    "Leo I of Rome",
    "Longinus the Centurion",
    "Louis IX of France",
    "Lucy of Syracuse",
    "Luke the Evangelist"
  ],
  "M-P": [
    "Macrina the Younger",
    "Marina the Great Martyr (Margaret of Antioch)",
    "Maria Goretti",
    "Mark the Evangelist",
    "Maron",
    "Martha of Bethany",
    "Martin of Tours",
    "Mary of Bethany",
    "Mary of Egypt",
    "Mary Magdalene",
    "Mary Magdalene de' Pazzi",
    "Matthew the Apostle",
    "Matthias the Apostle",
    "Maximus the Confessor",
    "Melania the Younger",
    "Melchior (Magi)",
    "Methodius (Apostle to the Slavs)",
    "Monica (Mother of St. Augustine)",
    "Nicholas of Myra",
    "Nicodemus the Pharisee",
    "Olga of Kiev",
    "Olivia of Palermo",
    "Onesimus of Byzantium",
    "Onuphrius The Great",
    "Optatus of Zaragoza",
    "Pantaleon (Panteleimon) of Nicomedia",
    "Papias of Hieropolis",
    "Pavel Gojdič",
    "Paul the Apostle",
    "Paul of the Cross",
    "Paula of Rome",
    "Perpetua of Carthage",
    "Peter the Apostle",
    "Peter I of Alexandria",
    "Philip the Apostle",
    "Philomena of Rome",
    "Pio of Pietrelcina",
    "Pius X of Rome",
    "Polycarp of Smyrna",
    "Priscilla of Corinth"
  ],
  "Q-Z": [
    "Romanos the Melodist",
    "Sabbas the Sanctified",
    "Scholastica (Foundress of the Benedictine Sisters)",
    "Sebastian the Martyr",
    "Sergius the Martyr",
    "Silas (Silvanus)",
    "Silvanus the Martyr",
    "Simon the Zealot",
    "Simeon of Jerusalem",
    "Simeon the God-Receiver of Jerusalem",
    "Simeon Stylites",
    "Simon the Apostle",
    "Sixtus II of Rome",
    "Stephen the First Martyr",
    "Sylvester I of Rome",
    "Tarcisius of Rome",
    "Tatiana of Rome",
    "Teresa of Avila",
    "Teresa of Calcutta",
    "Thecla of Iconium",
    "Therese of Lisieux",
    "Theodore Romzha",
    "Theodore the Studite",
    "Theodore the Varangian of Kiev",
    "Theodore the Recruit, Martyr",
    "Thomas the Apostle",
    "Thomas Becket of Canterbury",
    "Thomas More",
    "Timothy of Ephesus",
    "Titus of Crete",
    "Tryphon the Falconer of Lampsacus",
    "Valerian of Rome",
    "Valentine of Rome",
    "Victor of Damascus",
    "Victoria of Rome",
    "Vitus (Guy) the Martyr",
    "Vladimir of Kiev",
    "Wenceslaus",
    "Zachariah (Father of St. John the Baptist)"
  ]
}
